asyncore/__init__.py
asyncore/asyncore.py
pyasyncore-1.0.1.dist-info/LICENSE
pyasyncore-1.0.1.dist-info/METADATA
pyasyncore-1.0.1.dist-info/WHEEL
pyasyncore-1.0.1.dist-info/top_level.txt
pyasyncore-1.0.1.dist-info/RECORD
