Metadata-Version: 2.1
Name: pyasyncore
Version: 1.0.1
Summary: Make asyncore available for Python 3.12 onwards
Home-page: https://github.com/simonrob/pyasyncore
Author: Simon Robinson
Author-email: simon@robinson.ac
License: Python Software Foundation License Version 2
Platform: any
Classifier: Development Status :: 5 - Production/Stable
Classifier: License :: OSI Approved :: Python Software Foundation License
Classifier: Programming Language :: Python :: 3.12
License-File: LICENSE
